ks_nlp/__init__.py
ks_nlp/scraping.py
ks_nlp-0.0.1.dist-info/LICENSE
ks_nlp-0.0.1.dist-info/METADATA
ks_nlp-0.0.1.dist-info/WHEEL
ks_nlp-0.0.1.dist-info/top_level.txt
ks_nlp-0.0.1.dist-info/RECORD
